takodachi/__init__.py
takodachi/api.py
takodachi/cache.py
takodachi/ch.py
takodachi/chat.py
takodachi/currency.py
takodachi/dynamics.py
takodachi/kgall.py
takodachi/parse.py
takodachi/plot.py
takodachi-0.0.3.dist-info/LICENSE.txt
takodachi-0.0.3.dist-info/METADATA
takodachi-0.0.3.dist-info/WHEEL
takodachi-0.0.3.dist-info/top_level.txt
takodachi-0.0.3.dist-info/RECORD
