Metadata-Version: 2.1
Name: takodachi
Version: 0.0.3
Summary: hololive-analytics
Home-page: UNKNOWN
Author: xousz
License: UNKNOWN
Platform: UNKNOWN
Classifier: Programming Language :: Python :: 3
Classifier: License :: OSI Approved :: MIT License
Requires-Python: >=3.6
License-File: LICENSE.txt
Requires-Dist: google-api-python-client
